LICENSE
MANIFEST.in
README.rst
dev_requirements.txt
requirements.txt
setup.cfg
setup.py
./lockchain/__init__.py
./tests/__init__.py
./tests/test_lockchain.py
lockchain.egg-info/PKG-INFO
lockchain.egg-info/SOURCES.txt
lockchain.egg-info/dependency_links.txt
lockchain.egg-info/top_level.txt